MANIFEST.in
setup.cfg
setup.py
docs/api.rst
docs/conf.py
docs/index.rst
docs/news.rst
docs/examples/basic.rst
docs/examples/export.rst
keepassdb/__init__.py
keepassdb/__init__.pyc
keepassdb/const.py
keepassdb/const.pyc
keepassdb/db.py
keepassdb/db.pyc
keepassdb/exc.py
keepassdb/exc.pyc
keepassdb/model.py
keepassdb/model.pyc
keepassdb/structs.py
keepassdb/structs.pyc
keepassdb/util.py
keepassdb/util.pyc
keepassdb.egg-info/PKG-INFO
keepassdb.egg-info/SOURCES.txt
keepassdb.egg-info/dependency_links.txt
keepassdb.egg-info/requires.txt
keepassdb.egg-info/top_level.txt
keepassdb/__pycache__/__init__.cpython-32.pyc
keepassdb/export/__init__.py
keepassdb/export/__init__.pyc
keepassdb/export/xml.py
keepassdb/export/xml.pyc
keepassdb/tests/__init__.py
keepassdb/tests/__init__.pyc
keepassdb/tests/test_db.py
keepassdb/tests/test_db.pyc
keepassdb/tests/test_entries.py
keepassdb/tests/test_entries.pyc
keepassdb/tests/test_export_xml.py
keepassdb/tests/test_export_xml.pyc
keepassdb/tests/test_groups.py
keepassdb/tests/test_groups.pyc
keepassdb/tests/__pycache__/__init__.cpython-32.pyc
keepassdb/tests/__pycache__/test_db.cpython-32.pyc
keepassdb/tests/__pycache__/test_entries.cpython-32.pyc
keepassdb/tests/__pycache__/test_export_xml.cpython-32.pyc
keepassdb/tests/__pycache__/test_groups.cpython-32.pyc
keepassdb/tests/resources/example.kdb
keepassdb/tests/resources/example.xml